hocine7779_first_package/__init__.py
hocine7779_first_package/main.py
hocine7779_first_package-0.1.0.dist-info/METADATA
hocine7779_first_package-0.1.0.dist-info/WHEEL
hocine7779_first_package-0.1.0.dist-info/entry_points.txt
hocine7779_first_package-0.1.0.dist-info/top_level.txt
hocine7779_first_package-0.1.0.dist-info/RECORD
